<?xml version="1.0"?>
<pc:PackageCreator xmlns:mi="http://www.composite.net/ns/management/packageinstaller/1.0" xmlns:pc="http://www.composite.net/ns/management/packagecreator/2.0" xmlns:help="http://www.composite.net/ns/help/1.0">
	<pc:Files>
		<Add name="RemoveRedunantPaths.aspx" />
		<Add name="StoreCurrentPaths.aspx" />
	</pc:Files>
	<pc:Directories>
		<Add name="Frontend\Composite\Tools\LegacyUrlHandler\" />
	</pc:Directories>
	<pc:PackageFragmentInstallers>
		<mi:Add installerType="Composite.Core.PackageSystem.PackageFragmentInstallers.FileXslTransformationPackageFragmentInstaller, Composite" uninstallerType="Composite.Core.PackageSystem.PackageFragmentInstallers.FileXslTransformationPackageFragmentUninstaller, Composite" Ordering="10">
			<XslFiles>
				<XslFile pathXml="~\Web.config" installXsl="~\Config\Install.xsl" />
			</XslFiles>
		</mi:Add>
	</pc:PackageFragmentInstallers>
	<mi:PackageRequirements minimumCompositeVersion="2.0.3993.21339" maximumCompositeVersion="2.9.9" />
	<mi:PackageInformation name="Composite.Tools.LegacyUrlHandler" groupName="Composite.Tools" version="1.0.8" author="Composite A/S" website="http://composite.net" id="f0de8a66-23b8-41de-8cdc-9dc6d4395022" canBeUninstalled="true" systemLocking="hard" flushOnCompletion="false">
		<Description>Legacy url handler</Description>
	</mi:PackageInformation>
</pc:PackageCreator>